digit2chinese/__init__.py
digit2chinese-2023.1.20.13.dist-info/LICENSE
digit2chinese-2023.1.20.13.dist-info/METADATA
digit2chinese-2023.1.20.13.dist-info/WHEEL
digit2chinese-2023.1.20.13.dist-info/top_level.txt
digit2chinese-2023.1.20.13.dist-info/RECORD
