Metadata-Version: 2.1
Name: digit2chinese
Version: 2023.1.20.13
Summary: Convert numbers into uppercase Chinese characters
Home-page: https://gitee.com/yanchengxin2018/digit2chinese
Author: YanChengxin
Author-email: yanchengxin@yeah.net
Project-URL: Bug Tracker, https://gitee.com/yanchengxin2018/digit2chinese
Classifier: Programming Language :: Python :: 3
Classifier: License :: OSI Approved :: MIT License
Classifier: Operating System :: OS Independent
Requires-Python: >=3.6
License-File: LICENSE
